async_pybatis_orm/__init__.py
async_pybatis_orm/fields.py
async_pybatis_orm/base/__init__.py
async_pybatis_orm/base/abstracts.py
async_pybatis_orm/base/base_model.py
async_pybatis_orm/base/common_model.py
async_pybatis_orm/base/connection.py
async_pybatis_orm/base/database_manager.py
async_pybatis_orm/base/global_config.py
async_pybatis_orm/base/integrated_model.py
async_pybatis_orm/base/sql_builder.py
async_pybatis_orm/crud/__init__.py
async_pybatis_orm/crud/base_crud.py
async_pybatis_orm/crud/batch_crud.py
async_pybatis_orm/crud/condition_crud.py
async_pybatis_orm/crud/crud_model.py
async_pybatis_orm/crud/delete_mixin.py
async_pybatis_orm/crud/insert_mixin.py
async_pybatis_orm/crud/select_mixin.py
async_pybatis_orm/crud/update_mixin.py
async_pybatis_orm/pagination/__init__.py
async_pybatis_orm/pagination/page.py
async_pybatis_orm/pagination/page_helper.py
async_pybatis_orm/pagination/page_result.py
async_pybatis_orm/wrapper/__init__.py
async_pybatis_orm/wrapper/base_wrapper.py
async_pybatis_orm/wrapper/query_wrapper.py
async_pybatis_orm-2.0.1.dist-info/METADATA
async_pybatis_orm-2.0.1.dist-info/WHEEL
async_pybatis_orm-2.0.1.dist-info/top_level.txt
async_pybatis_orm-2.0.1.dist-info/RECORD
