Metadata-Version: 2.4
Name: async-pybatis-orm
Version: 2.0.1
Summary: 一个基于 MySQL 异步场景，对齐 MyBatis-Plus 语法风格的 Python ORM 框架
Author: lipop
License: MIT
Project-URL: Homepage, https://github.com/zhonglunsheng/async-pybatis-orm
Project-URL: Documentation, https://async-pybatis-orm.readthedocs.io
Project-URL: Repository, https://github.com/zhonglunsheng/async-pybatis-orm
Project-URL: Issues, https://github.com/zhonglunsheng/async-pybatis-orm/issues
Keywords: async,orm,mysql,database,aiomysql,asyncio,mybatis-plus,mapper,crud,query,pagination
Classifier: Development Status :: 4 - Beta
Classifier: Intended Audience :: Developers
Classifier: License :: OSI Approved :: MIT License
Classifier: Operating System :: OS Independent
Classifier: Programming Language :: Python :: 3.10
Classifier: Programming Language :: Python :: 3.11
Classifier: Programming Language :: Python :: 3.12
Classifier: Topic :: Database
Classifier: Topic :: Software Development :: Libraries :: Python Modules
Classifier: Framework :: AsyncIO
Requires-Python: >=3.8
Requires-Dist: databases>=0.7.0
Requires-Dist: aiomysql>=0.2.0
Requires-Dist: typing-extensions>=4.0.0
Requires-Dist: pytest>=8.3.5
Requires-Dist: pytest-asyncio>=0.24.0
Requires-Dist: cryptography>=46.0.2
Requires-Dist: black>=24.8.0
Provides-Extra: dev
Requires-Dist: pytest>=6.0; extra == "dev"
Requires-Dist: pytest-asyncio>=0.18.0; extra == "dev"
Requires-Dist: pytest-mock>=3.6.0; extra == "dev"
Requires-Dist: black>=22.0; extra == "dev"
Requires-Dist: isort>=5.10; extra == "dev"
Requires-Dist: flake8>=4.0; extra == "dev"
Requires-Dist: mypy>=0.950; extra == "dev"
Provides-Extra: docs
Requires-Dist: sphinx>=4.0; extra == "docs"
Requires-Dist: sphinx-rtd-theme>=1.0; extra == "docs"
Provides-Extra: all
Requires-Dist: async-pybatis-orm[dev,docs]; extra == "all"
